google_speech_pyplay/__init__.py
google_speech_pyplay/config.py
google_speech_pyplay/preloader_thread.py
google_speech_pyplay/speech.py
google_speech_pyplay/speech_segment.py
google_speech_pyplay/version.py
google_speech_pyplay-1.0.15.dist-info/licenses/LICENSE
tests/__init__.py
google_speech_pyplay-1.0.15.dist-info/METADATA
google_speech_pyplay-1.0.15.dist-info/WHEEL
google_speech_pyplay-1.0.15.dist-info/top_level.txt
google_speech_pyplay-1.0.15.dist-info/RECORD
