Metadata-Version: 2.4
Name: google_speech_pyplay
Version: 1.0.15
Summary: Text-to-speech synthesis using the Google Translate TTS API and pygame.
Author-email: Karim Aziiev <karim.aziiev@gmail.com>
License: GNU
Keywords: speech,pygame,audio,synthesis,voice,google,tts
License-File: LICENSE
Requires-Dist: appdirs>=1.4.0
Requires-Dist: requests>=2.6.0
Requires-Dist: web_cache>=1.1.0
Requires-Dist: pygame
Provides-Extra: dev
Requires-Dist: black; extra == "dev"
Requires-Dist: isort; extra == "dev"
Requires-Dist: pre-commit; extra == "dev"
Dynamic: license-file
